[{
    "_id": "610f632b0112f1b4448d9671",
    "applicant": 123,
    "company": "mHealthBank",
    "currency": "SGD",
    "end_sal": 35000000,
    "exp_min": 5,
    "exp_opt": 10,
    "last_updated": 270,
    "location": "Jakarta",
    "start_sal": 25000000,
    "title": "Solution Architect"
},{
    "_id": "610f632b0112f1b4448d9672",
    "applicant": 16,
    "company": "Pt Digital Agensi Nusantara",
    "currency": "IDR",
    "end_sal": 5000000,
    "exp_min": null,
    "exp_opt": null,
    "last_updated": 9,
    "location": "Bandung",
    "start_sal": 3000000,
    "title": "Flutter Developer"
},{
    "_id": "610f632b0112f1b4448d9673",
    "applicant": 3,
    "company": "Hzn",
    "currency": "IDR",
    "end_sal": 12000000,
    "exp_min": 1,
    "exp_opt": 3,
    "last_updated": 6,
    "location": "Tangerang",
    "start_sal": 7000000,
    "title": "Software Development Engineer I - Backend"
},{
    "_id": "610f632b0112f1b4448d9674",
    "applicant": 51,
    "company": "Pt Cogworx Business Performance Consulting",
    "currency": "IDR",
    "end_sal": null,
    "exp_min": 3,
    "exp_opt": 5,
    "last_updated": 2,
    "location": "Tangerang",
    "start_sal": "10.000.000",
    "title": "Network Engineer"
},{
    "_id": "610f632b0112f1b4448d9675",
    "applicant": 27,
    "company": "Ninja Xpress",
    "currency": null,
    "end_sal": null,
    "exp_min": 3,
    "exp_opt": 5,
    "last_updated": 20,
    "location": "Jakarta",
    "start_sal": null,
    "title": "Software Tester"
},{
    "_id": "610f632b0112f1b4448d9676",
    "applicant": 4,
    "company": "Jatis Mobile",
    "currency": "IDR",
    "end_sal": 5678,
    "exp_min": 3,
    "exp_opt": 5,
    "last_updated": 11,
    "location": "Jakarta",
    "start_sal": 1234,
    "title": "Backend Developer"
},{
    "_id": "610f632b0112f1b4448d9677",
    "applicant": 31,
    "company": "Ylearn",
    "currency": "IDR",
    "end_sal": 8000000,
    "exp_min": 1,
    "exp_opt": 3,
    "last_updated": 2,
    "location": "Jakarta",
    "start_sal": 6000000,
    "title": "Backend Engineer"
},{
    "_id": "610f632b0112f1b4448d9678",
    "applicant": 24,
    "company": "Pt Total Cipta Persada",
    "currency": "IDR",
    "end_sal": 7000000,
    "exp_min": 3,
    "exp_opt": 5,
    "last_updated": 2,
    "location": "Surabaya",
    "start_sal": 6500000,
    "title": "Frontend Developer"
},{
    "_id": "610f632b0112f1b4448d9679",
    "applicant": 28,
    "company": "PT. Ebdesk Teknologi",
    "currency": "IDR",
    "end_sal": 5000000,
    "exp_min": 0,
    "exp_opt": 1,
    "last_updated": 3,
    "location": "Tangerang",
    "start_sal": 4500000,
    "title": "Back End PROGRAMMER"
},{
    "_id": "610f632b0112f1b4448d967a",
    "applicant": 9,
    "company": "AccelByte Inc",
    "currency": null,
    "end_sal": null,
    "exp_min": 3,
    "exp_opt": 5,
    "last_updated": 5,
    "location": "Yogyakarta",
    "start_sal": null,
    "title": "Software Development Engineer C++"
},{
    "_id": "610f632b0112f1b4448d967b",
    "applicant": 16,
    "company": "Landx",
    "currency": null,
    "end_sal": null,
    "exp_min": 1,
    "exp_opt": 3,
    "last_updated": 24,
    "location": "Jakarta",
    "start_sal": null,
    "title": "Software Engineer"
},{
    "_id": "610f632b0112f1b4448d967c",
    "applicant": 43,
    "company": "XCIDIC",
    "currency": null,
    "end_sal": null,
    "exp_min": 0,
    "exp_opt": 1,
    "last_updated": 1,
    "location": "Jakarta",
    "start_sal": null,
    "title": "Software Developer Intern"
},{
    "_id": "610f632b0112f1b4448d967d",
    "applicant": 11,
    "company": "Peakflo",
    "currency": null,
    "end_sal": null,
    "exp_min": 3,
    "exp_opt": 5,
    "last_updated": 13,
    "location": "Jakarta",
    "start_sal": null,
    "title": "Fullstack Developer (REMOTE)"
},{
    "_id": "610f632b0112f1b4448d967e",
    "applicant": 1,
    "company": "Nostratech",
    "currency": null,
    "end_sal": null,
    "exp_min": 3,
    "exp_opt": 5,
    "last_updated": 13,
    "location": "Jakarta",
    "start_sal": null,
    "title": "Back End Engineer Mid - Senior (Springboot)"
},{
    "_id": "610f632b0112f1b4448d967f",
    "applicant": 30,
    "company": "CV. Zahira Solusi Informatika",
    "currency": null,
    "end_sal": null,
    "exp_min": 1,
    "exp_opt": 3,
    "last_updated": 1,
    "location": "Jakarta",
    "start_sal": null,
    "title": "PHP Web Developer (Laravel Framework)"
},{
    "_id": "610f632b0112f1b4448d9680",
    "applicant": 90,
    "company": "PT. Bilna (Orami)",
    "currency": "IDR",
    "end_sal": 15000000,
    "exp_min": 1,
    "exp_opt": 3,
    "last_updated": 30,
    "location": "South Tangerang",
    "start_sal": 0,
    "title": "Middle Backend Developer"
},{
    "_id": "610f632b0112f1b4448d9681",
    "applicant": 22,
    "company": "Binar Academy",
    "currency": "IDR",
    "end_sal": 12000000,
    "exp_min": 3,
    "exp_opt": 5,
    "last_updated": 26,
    "location": "Jakarta",
    "start_sal": 8000000,
    "title": "Android Developer"
},{
    "_id": "610f632b0112f1b4448d9682",
    "applicant": 14,
    "company": "JMC IT Consultant",
    "currency": "IDR",
    "end_sal": 4500000,
    "exp_min": null,
    "exp_opt": null,
    "last_updated": 20,
    "location": "Yogyakarta",
    "start_sal": 2750000,
    "title": "Programmer"
},{
    "_id": "610f632b0112f1b4448d9683",
    "applicant": 9,
    "company": "Pt. Adira Dinamika Multifinance, Tbk",
    "currency": null,
    "end_sal": null,
    "exp_min": 1,
    "exp_opt": 3,
    "last_updated": 25,
    "location": "Jakarta",
    "start_sal": null,
    "title": "Digital Engineering Specialist "
},{
    "_id": "610f632b0112f1b4448d9684",
    "applicant": 2,
    "company": "Hzn",
    "currency": "IDR",
    "end_sal": 20000000,
    "exp_min": 3,
    "exp_opt": 5,
    "last_updated": 6,
    "location": "Tangerang",
    "start_sal": 12000000,
    "title": "Software Development Engineer II - Backend"
},{
    "_id": "610f632b0112f1b4448d9685",
    "applicant": 36,
    "company": "Arvis",
    "currency": "IDR",
    "end_sal": 10000000,
    "exp_min": 1,
    "exp_opt": 3,
    "last_updated": null,
    "location": "Jakarta",
    "start_sal": 6000000,
    "title": "React Native Developer"
},{
    "_id": "610f632b0112f1b4448d9686",
    "applicant": 6,
    "company": "Prosa.ai",
    "currency": "IDR",
    "end_sal": 15000000,
    "exp_min": 1,
    "exp_opt": 3,
    "last_updated": 7,
    "location": "Bandung",
    "start_sal": 8000000,
    "title": "Full Stack Engineer"
},{
    "_id": "610f632b0112f1b4448d9687",
    "applicant": 36,
    "company": "Pt Linov Roket Prestasi",
    "currency": "IDR",
    "end_sal": 9000000,
    "exp_min": 1,
    "exp_opt": 3,
    "last_updated": 2,
    "location": "Tebet, Jakarta",
    "start_sal": 5000000,
    "title": "Front End Developer"
},{
    "_id": "610f632b0112f1b4448d9688",
    "applicant": 64,
    "company": "The Puzzlers",
    "currency": "IDR",
    "end_sal": 20000000,
    "exp_min": null,
    "exp_opt": null,
    "last_updated": 1,
    "location": "Denpasar",
    "start_sal": 10000000,
    "title": "Node.js Backend Developer"
},{
    "_id": "610f632b0112f1b4448d9689",
    "applicant": 5,
    "company": "PT. Asian Sigma Technology",
    "currency": "IDR",
    "end_sal": 11000000,
    "exp_min": 1,
    "exp_opt": 3,
    "last_updated": 4,
    "location": "Sunter, Jakarta",
    "start_sal": 8000000,
    "title": "QA Automation"
},{
    "_id": "610f632b0112f1b4448d968a",
    "applicant": 14,
    "company": "Waktukita.com",
    "currency": "IDR",
    "end_sal": 15000000,
    "exp_min": 1,
    "exp_opt": 3,
    "last_updated": 24,
    "location": "Jakarta",
    "start_sal": 8000000,
    "title": "Fullstack Developer (Fintech Company)"
},{
    "_id": "610f632b0112f1b4448d968b",
    "applicant": 231,
    "company": "PT Code Development Indonesia",
    "currency": null,
    "end_sal": null,
    "exp_min": 1,
    "exp_opt": 3,
    "last_updated": 1,
    "location": "Jakarta",
    "start_sal": null,
    "title": "QA Manual"
},{
    "_id": "610f632b0112f1b4448d968c",
    "applicant": 65,
    "company": "CPR Vision Management Pte Ltd",
    "currency": "IDR",
    "end_sal": 15000000,
    "exp_min": 3,
    "exp_opt": 5,
    "last_updated": 26,
    "location": "Batam",
    "start_sal": 0,
    "title": "Fullstack Developer (Remote during covid 19)"
},{
    "_id": "610f632b0112f1b4448d968d",
    "applicant": 22,
    "company": "Pt Eigen Trimathema",
    "currency": "IDR",
    "end_sal": 7000000,
    "exp_min": 1,
    "exp_opt": 3,
    "last_updated": 4,
    "location": "Bandung",
    "start_sal": 4000000,
    "title": "FULLSTACK DEVELOPER"
},{
    "_id": "610f632b0112f1b4448d968e",
    "applicant": 37,
    "company": "Waktukita.com",
    "currency": "IDR",
    "end_sal": 27000000,
    "exp_min": 5,
    "exp_opt": 10,
    "last_updated": 3,
    "location": "Jakarta",
    "start_sal": 20000000,
    "title": "Head of IT (Fintech Company)"
},{
    "_id": "610f632b0112f1b4448d968f",
    "applicant": 218,
    "company": "PT Code Development Indonesia",
    "currency": null,
    "end_sal": null,
    "exp_min": 1,
    "exp_opt": 3,
    "last_updated": 2,
    "location": "Jakarta",
    "start_sal": null,
    "title": "Business Analyst"
},{
    "_id": "610f632b0112f1b4448d9690",
    "applicant": 207,
    "company": "Get",
    "currency": null,
    "end_sal": null,
    "exp_min": 0,
    "exp_opt": 1,
    "last_updated": 60,
    "location": "Jakarta",
    "start_sal": null,
    "title": "QA Tester"
},{
    "_id": "610f632b0112f1b4448d9691",
    "applicant": 1,
    "company": "Jakarta Web Solution",
    "currency": null,
    "end_sal": null,
    "exp_min": 3,
    "exp_opt": 5,
    "last_updated": 9,
    "location": "Jakarta",
    "start_sal": null,
    "title": "Senior Software Engineer"
},{
    "_id": "610f632b0112f1b4448d9692",
    "applicant": 68,
    "company": "Pt Linov Roket Prestasi",
    "currency": null,
    "end_sal": null,
    "exp_min": 0,
    "exp_opt": 1,
    "last_updated": 1,
    "location": "Tebet, Jakarta",
    "start_sal": null,
    "title": "IT Intern (Programmer)"
},{
    "_id": "610f632b0112f1b4448d9693",
    "applicant": 3,
    "company": "Dhana Jasa Konsultan",
    "currency": "IDR",
    "end_sal": 28000000,
    "exp_min": 5,
    "exp_opt": 10,
    "last_updated": 10,
    "location": "Abang",
    "start_sal": 15000000,
    "title": "IT Business Analyst"
},{
    "_id": "610f632b0112f1b4448d9694",
    "applicant": 2,
    "company": "Hzn",
    "currency": "IDR",
    "end_sal": 12000000,
    "exp_min": 1,
    "exp_opt": 3,
    "last_updated": 6,
    "location": "Tangerang",
    "start_sal": 7000000,
    "title": "Software Test Engineer I - Backend (Automation)"
},{
    "_id": "610f632b0112f1b4448d9695",
    "applicant": 164,
    "company": "PT NUSA INTI SATU ARTHA (DOKU)",
    "currency": null,
    "end_sal": null,
    "exp_min": 1,
    "exp_opt": 3,
    "last_updated": null,
    "location": "Jakarta",
    "start_sal": null,
    "title": "Database Administrator Engineer"
},{
    "_id": "610f632b0112f1b4448d9696",
    "applicant": 28,
    "company": "Pt Platinumetrix Global Inovasi",
    "currency": "IDR",
    "end_sal": 15000000,
    "exp_min": 1,
    "exp_opt": 3,
    "last_updated": 3,
    "location": "Jakarta",
    "start_sal": 7500000,
    "title": "Big Data Operations"
},{
    "_id": "610f632b0112f1b4448d9697",
    "applicant": 6,
    "company": "PT Mplus Solusi Perdana",
    "currency": "IDR",
    "end_sal": 11000000,
    "exp_min": 1,
    "exp_opt": 3,
    "last_updated": 4,
    "location": "Jakarta",
    "start_sal": 6000000,
    "title": "Python Developer"
},{
    "_id": "610f632b0112f1b4448d9698",
    "applicant": 6,
    "company": "Takalab",
    "currency": "IDR",
    "end_sal": 15000000,
    "exp_min": 3,
    "exp_opt": 5,
    "last_updated": 6,
    "location": "Mampang Prapatan, Jakarta",
    "start_sal": 10000000,
    "title": "Senior Front-End Developer / Leader"
},{
    "_id": "610f632b0112f1b4448d9699",
    "applicant": 38,
    "company": "Pt. Adira Dinamika Multifinance, Tbk",
    "currency": null,
    "end_sal": null,
    "exp_min": 3,
    "exp_opt": 5,
    "last_updated": 30,
    "location": "Jakarta",
    "start_sal": null,
    "title": "Programmer - IT Loan Origination"
},{
    "_id": "610f632b0112f1b4448d969a",
    "applicant": 2,
    "company": "PT Visionet Data Internasional",
    "currency": null,
    "end_sal": null,
    "exp_min": 5,
    "exp_opt": 10,
    "last_updated": 30,
    "location": "Tangerang",
    "start_sal": null,
    "title": "Senior Infra & Hybrid Cloud Presales Manager"
},{
    "_id": "610f632b0112f1b4448d969b",
    "applicant": 60,
    "company": "Pt Linov Roket Prestasi",
    "currency": null,
    "end_sal": null,
    "exp_min": 1,
    "exp_opt": 3,
    "last_updated": 1,
    "location": "Jakarta",
    "start_sal": null,
    "title": "Technical Writer"
},{
    "_id": "610f632b0112f1b4448d969c",
    "applicant": 15,
    "company": "Sekawan Media",
    "currency": null,
    "end_sal": null,
    "exp_min": 1,
    "exp_opt": 3,
    "last_updated": 13,
    "location": "Malang",
    "start_sal": null,
    "title": "Fulltstack Developer"
},{
    "_id": "610f632b0112f1b4448d969d",
    "applicant": 576,
    "company": "PT Stampindo Lancar Jaya",
    "currency": "IDR",
    "end_sal": 8000000,
    "exp_min": null,
    "exp_opt": null,
    "last_updated": 1,
    "location": "Jakarta",
    "start_sal": 4500000,
    "title": "Junior Programmer "
},{
    "_id": "610f632b0112f1b4448d969e",
    "applicant": 49,
    "company": "PT. PMA Born Digital",
    "currency": "IDR",
    "end_sal": 7000000,
    "exp_min": 1,
    "exp_opt": 3,
    "last_updated": null,
    "location": "Yogyakarta",
    "start_sal": 3000000,
    "title": "Backend Web Developer"
},{
    "_id": "610f632b0112f1b4448d969f",
    "applicant": 42,
    "company": "PT NUSA INTI SATU ARTHA (DOKU)",
    "currency": null,
    "end_sal": null,
    "exp_min": 0,
    "exp_opt": 1,
    "last_updated": 2,
    "location": "Jakarta",
    "start_sal": null,
    "title": "Internship Technical Writer Engineer"
},{
    "_id": "610f632b0112f1b4448d96a0",
    "applicant": 4,
    "company": "Pt. Dhana Jasa Konsultan",
    "currency": "IDR",
    "end_sal": 11000000,
    "exp_min": 1,
    "exp_opt": 3,
    "last_updated": 9,
    "location": "Jakarta",
    "start_sal": 8000000,
    "title": "Siebel QA"
},{
    "_id": "610f632b0112f1b4448d96a1",
    "applicant": 19,
    "company": "Jakarta Web Solution",
    "currency": null,
    "end_sal": null,
    "exp_min": 1,
    "exp_opt": 3,
    "last_updated": 10,
    "location": "Jakarta",
    "start_sal": null,
    "title": "Junior Data Developer"
},{
    "_id": "610f632b0112f1b4448d96a2",
    "applicant": 290,
    "company": "PT. Teknologi Kode Indonesia",
    "currency": "IDR",
    "end_sal": 5500000,
    "exp_min": 1,
    "exp_opt": 3,
    "last_updated": 2,
    "location": "Yogyakarta",
    "start_sal": 4500000,
    "title": "QA Tester"
},{
    "_id": "610f632b0112f1b4448d96a3",
    "applicant": 32,
    "company": "My Hunter",
    "currency": "IDR",
    "end_sal": 10000000,
    "exp_min": 1,
    "exp_opt": 3,
    "last_updated": 3,
    "location": "Jakarta",
    "start_sal": 5000000,
    "title": "Java Developer (Backend)"
},{
    "_id": "610f632b0112f1b4448d96a4",
    "applicant": 41,
    "company": "Pt Linov Roket Prestasi",
    "currency": null,
    "end_sal": null,
    "exp_min": 3,
    "exp_opt": 5,
    "last_updated": null,
    "location": "Jakarta",
    "start_sal": null,
    "title": "PHP Developer "
},{
    "_id": "610f632b0112f1b4448d96a5",
    "applicant": 89,
    "company": "Designcub3",
    "currency": null,
    "end_sal": null,
    "exp_min": null,
    "exp_opt": null,
    "last_updated": 1,
    "location": "Jakarta",
    "start_sal": null,
    "title": "Website Programmer"
},{
    "_id": "610f632b0112f1b4448d96a6",
    "applicant": 170,
    "company": "Bangunindo Teknusa Jaya",
    "currency": null,
    "end_sal": null,
    "exp_min": 1,
    "exp_opt": 3,
    "last_updated": 26,
    "location": "Jakarta",
    "start_sal": null,
    "title": "Backend Developer"
},{
    "_id": "610f632b0112f1b4448d96a7",
    "applicant": 4,
    "company": "PT. Cudo Communications",
    "currency": "IDR",
    "end_sal": 12000000,
    "exp_min": 1,
    "exp_opt": 3,
    "last_updated": 10,
    "location": "Jakarta",
    "start_sal": 4000000,
    "title": "Production Environment"
},{
    "_id": "610f632b0112f1b4448d96a8",
    "applicant": 41,
    "company": "Pt Amanah Karya Indonesia",
    "currency": "IDR",
    "end_sal": 7000000,
    "exp_min": 1,
    "exp_opt": 3,
    "last_updated": 1,
    "location": "Depok",
    "start_sal": 5000000,
    "title": "Full-Stack Developer"
},{
    "_id": "610f632b0112f1b4448d96a9",
    "applicant": 60,
    "company": "Vouch SG Pte Ltd",
    "currency": null,
    "end_sal": null,
    "exp_min": 1,
    "exp_opt": 3,
    "last_updated": 30,
    "location": "Jakarta",
    "start_sal": null,
    "title": "Software Tester (REMOTE)"
},{
    "_id": "610f632b0112f1b4448d96aa",
    "applicant": 9,
    "company": "Friendchised Indonesia",
    "currency": "IDR",
    "end_sal": 10000000,
    "exp_min": 1,
    "exp_opt": 3,
    "last_updated": 5,
    "location": "Jakarta",
    "start_sal": 6000000,
    "title": "Fullstack Developer"
},{
    "_id": "610f632b0112f1b4448d96ab",
    "applicant": 95,
    "company": "XCIDIC",
    "currency": "IDR",
    "end_sal": 15000000,
    "exp_min": 3,
    "exp_opt": 5,
    "last_updated": 30,
    "location": "Jakarta",
    "start_sal": 7000000,
    "title": "Software Developer "
},{
    "_id": "610f632b0112f1b4448d96ac",
    "applicant": 2,
    "company": "SIRCLO",
    "currency": null,
    "end_sal": null,
    "exp_min": 1,
    "exp_opt": 3,
    "last_updated": 5,
    "location": "Tangerang",
    "start_sal": null,
    "title": "Backend Developer"
},{
    "_id": "610f632b0112f1b4448d96ad",
    "applicant": 6,
    "company": "Pt Platinumetrix Global Inovasi",
    "currency": "IDR",
    "end_sal": 20000000,
    "exp_min": 5,
    "exp_opt": 10,
    "last_updated": 13,
    "location": "Jakarta",
    "start_sal": 10000000,
    "title": "Pre-Sales Lead "
},{
    "_id": "610f632b0112f1b4448d96ae",
    "applicant": 13,
    "company": "Digital Envision",
    "currency": "IDR",
    "end_sal": 15000000,
    "exp_min": 5,
    "exp_opt": 10,
    "last_updated": 6,
    "location": "Semarang",
    "start_sal": 8000000,
    "title": "Senior Fullstack Developer"
},{
    "_id": "610f632b0112f1b4448d96af",
    "applicant": 71,
    "company": "PT Verita Informatika",
    "currency": "IDR",
    "end_sal": 15000000,
    "exp_min": 1,
    "exp_opt": 3,
    "last_updated": 1,
    "location": "Tanah Abang, Jakarta",
    "start_sal": 8000000,
    "title": "Back End Developer"
},{
    "_id": "610f632b0112f1b4448d96b0",
    "applicant": 17,
    "company": "Typedream",
    "currency": "IDR",
    "end_sal": 20000000,
    "exp_min": 1,
    "exp_opt": 3,
    "last_updated": 3,
    "location": "Jakarta",
    "start_sal": 10000000,
    "title": "Frontend Engineer"
},{
    "_id": "610f632b0112f1b4448d96b1",
    "applicant": 81,
    "company": "PT. Asian Sigma Technology",
    "currency": "IDR",
    "end_sal": 8000000,
    "exp_min": 1,
    "exp_opt": 3,
    "last_updated": 2,
    "location": "Sunter, Jakarta",
    "start_sal": 6000000,
    "title": "QA Manual (Sunter)"
},{
    "_id": "610f632b0112f1b4448d96b2",
    "applicant": 5,
    "company": "Jakarta Web Solution",
    "currency": null,
    "end_sal": null,
    "exp_min": 3,
    "exp_opt": 5,
    "last_updated": 9,
    "location": "Jakarta",
    "start_sal": null,
    "title": "Senior Full Stack Developer "
},{
    "_id": "610f632b0112f1b4448d96b3",
    "applicant": 66,
    "company": "Brick - Financial Api",
    "currency": "IDR",
    "end_sal": 20000000,
    "exp_min": 1,
    "exp_opt": 3,
    "last_updated": 2,
    "location": "Jakarta",
    "start_sal": 10000000,
    "title": "Backend Developer"
},{
    "_id": "610f632b0112f1b4448d96b4",
    "applicant": 35,
    "company": "Atlaz",
    "currency": null,
    "end_sal": null,
    "exp_min": 1,
    "exp_opt": 3,
    "last_updated": 1,
    "location": "Tangerang",
    "start_sal": null,
    "title": "Web Developer"
},{
    "_id": "610f632b0112f1b4448d96b5",
    "applicant": 49,
    "company": "Ogya Tekno Nusantara",
    "currency": "IDR",
    "end_sal": 15000000,
    "exp_min": 3,
    "exp_opt": 5,
    "last_updated": 1,
    "location": "Jakarta",
    "start_sal": 9000000,
    "title": "Business Analyst"
},{
    "_id": "610f632b0112f1b4448d96b6",
    "applicant": 9,
    "company": "PT Indopasifik Teknologi Medika Indonesia",
    "currency": "IDR",
    "end_sal": 15000000,
    "exp_min": 1,
    "exp_opt": 3,
    "last_updated": 4,
    "location": "Kuningan, Jakarta",
    "start_sal": 12000000,
    "title": "Android Engineer"
},{
    "_id": "610f632b0112f1b4448d96b7",
    "applicant": 10,
    "company": "Avana Indonesia",
    "currency": "IDR",
    "end_sal": 15000000,
    "exp_min": 1,
    "exp_opt": 3,
    "last_updated": 23,
    "location": "Bandung",
    "start_sal": 8000000,
    "title": "Full Stack Developer"
},{
    "_id": "610f632b0112f1b4448d96b8",
    "applicant": 6,
    "company": "AIA Singapore Pte Ltd",
    "currency": null,
    "end_sal": null,
    "exp_min": 1,
    "exp_opt": 3,
    "last_updated": 9,
    "location": "Batam",
    "start_sal": null,
    "title": "Fullstack ReactJS (F)"
},{
    "_id": "610f632b0112f1b4448d96b9",
    "applicant": 19,
    "company": "Zipmex",
    "currency": null,
    "end_sal": null,
    "exp_min": 3,
    "exp_opt": 5,
    "last_updated": 25,
    "location": "Jakarta",
    "start_sal": null,
    "title": "Quality Assurance Engineer"
},{
    "_id": "610f632b0112f1b4448d96ba",
    "applicant": 13,
    "company": "Waktukita.com",
    "currency": "IDR",
    "end_sal": 20000000,
    "exp_min": 3,
    "exp_opt": 5,
    "last_updated": 30,
    "location": "Jakarta",
    "start_sal": 8000000,
    "title": "Golang Developer (IT Company)"
},{
    "_id": "610f632b0112f1b4448d96bb",
    "applicant": 48,
    "company": "PT Code Development Indonesia",
    "currency": null,
    "end_sal": null,
    "exp_min": 1,
    "exp_opt": 3,
    "last_updated": 3,
    "location": "Jakarta",
    "start_sal": null,
    "title": "SEO Specialist"
},{
    "_id": "610f632b0112f1b4448d96bc",
    "applicant": 11,
    "company": "Pijar Indonesia",
    "currency": "IDR",
    "end_sal": 10000000,
    "exp_min": 5,
    "exp_opt": 10,
    "last_updated": 27,
    "location": "Jakarta",
    "start_sal": 7000000,
    "title": "DevOps Engineer"
},{
    "_id": "610f632b0112f1b4448d96bd",
    "applicant": 7,
    "company": "Rimba Ananta Vikasa Indonesia",
    "currency": null,
    "end_sal": null,
    "exp_min": 1,
    "exp_opt": 3,
    "last_updated": 3,
    "location": "Penjaringan, Jakarta",
    "start_sal": null,
    "title": "Software Engineer"
},{
    "_id": "610f632b0112f1b4448d96be",
    "applicant": 67,
    "company": "PT Integrasi Inti Sinergi",
    "currency": "IDR",
    "end_sal": 15000000,
    "exp_min": 1,
    "exp_opt": 3,
    "last_updated": 2,
    "location": "Kemang, Jakarta",
    "start_sal": 7000000,
    "title": "Front End Developer"
},{
    "_id": "610f632b0112f1b4448d96bf",
    "applicant": 3,
    "company": "Centrinova Solusi Edukasi",
    "currency": "IDR",
    "end_sal": 10000000,
    "exp_min": 3,
    "exp_opt": 5,
    "last_updated": 10,
    "location": "Tangerang",
    "start_sal": 5000000,
    "title": "Unity Developer"
},{
    "_id": "610f632b0112f1b4448d96c0",
    "applicant": 8,
    "company": "Pt. Sinergi Digital Pusaka",
    "currency": null,
    "end_sal": null,
    "exp_min": 1,
    "exp_opt": 3,
    "last_updated": 12,
    "location": "Jakarta",
    "start_sal": null,
    "title": "System Analyst"
},{
    "_id": "610f632b0112f1b4448d96c1",
    "applicant": 7,
    "company": "PT. Asian Sigma Technology",
    "currency": "IDR",
    "end_sal": 12000000,
    "exp_min": 1,
    "exp_opt": 3,
    "last_updated": 4,
    "location": "Abang",
    "start_sal": 9000000,
    "title": "IT Project Management Officer (IT PMO)/IT BA"
},{
    "_id": "610f632b0112f1b4448d96c2",
    "applicant": 8,
    "company": "Prosa.ai",
    "currency": "IDR",
    "end_sal": 15000000,
    "exp_min": 1,
    "exp_opt": 3,
    "last_updated": 6,
    "location": "Bandung",
    "start_sal": 8000000,
    "title": "Backend Engineer"
},{
    "_id": "610f632b0112f1b4448d96c3",
    "applicant": 8,
    "company": "PT Widya Inovasi Indonesia",
    "currency": "IDR",
    "end_sal": 3500000,
    "exp_min": 1,
    "exp_opt": 3,
    "last_updated": 16,
    "location": "Yogyakarta",
    "start_sal": 2500000,
    "title": "AI Engineer Computer Vision ( WII )"
},{
    "_id": "610f632b0112f1b4448d96c4",
    "applicant": 5,
    "company": "Digital Envision",
    "currency": "IDR",
    "end_sal": 8000000,
    "exp_min": 1,
    "exp_opt": 3,
    "last_updated": 12,
    "location": "Semarang",
    "start_sal": 3000000,
    "title": "Backend Developer"
},{
    "_id": "610f632b0112f1b4448d96c5",
    "applicant": 105,
    "company": "AIA Singapore Pte Ltd",
    "currency": null,
    "end_sal": null,
    "exp_min": 0,
    "exp_opt": 1,
    "last_updated": 4,
    "location": "Batam",
    "start_sal": null,
    "title": "Database Developer Intern"
},{
    "_id": "610f632b0112f1b4448d96c6",
    "applicant": 18,
    "company": "Lifepal",
    "currency": "IDR",
    "end_sal": 30000000,
    "exp_min": 3,
    "exp_opt": 5,
    "last_updated": 11,
    "location": "Kemang, Jakarta",
    "start_sal": 10000000,
    "title": "Backend Engineer (Node.js)"
},{
    "_id": "610f632b0112f1b4448d96c7",
    "applicant": 1,
    "company": "Dhana Jasa Konsultan",
    "currency": "IDR",
    "end_sal": 35000000,
    "exp_min": 5,
    "exp_opt": 10,
    "last_updated": 12,
    "location": "Abang",
    "start_sal": 17000000,
    "title": "Software Architect"
},{
    "_id": "610f632b0112f1b4448d96c8",
    "applicant": 1,
    "company": "Dhana Jasa Konsultan",
    "currency": "IDR",
    "end_sal": 25000000,
    "exp_min": 3,
    "exp_opt": 5,
    "last_updated": 10,
    "location": "Abang",
    "start_sal": 12000000,
    "title": "OpenText Consultant"
},{
    "_id": "610f632b0112f1b4448d96c9",
    "applicant": 65,
    "company": "Pt. Kinerja Prima Nusantara",
    "currency": "IDR",
    "end_sal": 9000000,
    "exp_min": 1,
    "exp_opt": 3,
    "last_updated": null,
    "location": "Jakarta",
    "start_sal": 6000000,
    "title": "Software Quality Assurance"
},{
    "_id": "610f632b0112f1b4448d96ca",
    "applicant": 2,
    "company": "Human. E",
    "currency": null,
    "end_sal": null,
    "exp_min": 3,
    "exp_opt": 5,
    "last_updated": 9,
    "location": "Batam",
    "start_sal": null,
    "title": "QA Support"
},{
    "_id": "610f632b0112f1b4448d96cb",
    "applicant": 11,
    "company": "PT. Asian Sigma Technology",
    "currency": "IDR",
    "end_sal": 15000000,
    "exp_min": 3,
    "exp_opt": 5,
    "last_updated": 5,
    "location": "Sunter, Jakarta",
    "start_sal": 12000000,
    "title": "Fullstack Developer (Sunter)"
},{
    "_id": "610f632b0112f1b4448d96cc",
    "applicant": 9,
    "company": "Jatis Mobile",
    "currency": "IDR",
    "end_sal": 5678,
    "exp_min": 1,
    "exp_opt": 3,
    "last_updated": 16,
    "location": "Jakarta",
    "start_sal": 1234,
    "title": "Software Engineer"
},{
    "_id": "610f632b0112f1b4448d96cd",
    "applicant": 3,
    "company": "PT. Teknologi Kode Indonesia",
    "currency": "IDR",
    "end_sal": 5500000,
    "exp_min": 1,
    "exp_opt": 3,
    "last_updated": 9,
    "location": "Yogyakarta",
    "start_sal": 4000000,
    "title": "Full-Stack Engineer"
},{
    "_id": "610f632b0112f1b4448d96ce",
    "applicant": 5,
    "company": "Dhana Jasa Konsultan",
    "currency": "IDR",
    "end_sal": 25000000,
    "exp_min": 3,
    "exp_opt": 5,
    "last_updated": 12,
    "location": "Abang",
    "start_sal": 12000000,
    "title": "Siebel QA"
},{
    "_id": "610f632b0112f1b4448d96cf",
    "applicant": 83,
    "company": "Pt Majapahit Teknologi Nusantara",
    "currency": "IDR",
    "end_sal": 10000000,
    "exp_min": 1,
    "exp_opt": 3,
    "last_updated": 1,
    "location": "Cakung, Jakarta",
    "start_sal": 6000000,
    "title": "System Analyst IT"
},{
    "_id": "610f632b0112f1b4448d96d0",
    "applicant": 2,
    "company": "Dhana Jasa Konsultan",
    "currency": "IDR",
    "end_sal": 25000000,
    "exp_min": 3,
    "exp_opt": 5,
    "last_updated": 10,
    "location": "Abang",
    "start_sal": 10000000,
    "title": "ETL Developer"
},{
    "_id": "610f632b0112f1b4448d96d1",
    "applicant": 2,
    "company": "PT. Indo Teknologi Utama",
    "currency": "IDR",
    "end_sal": 40000000,
    "exp_min": 5,
    "exp_opt": 10,
    "last_updated": 5,
    "location": "Jakarta",
    "start_sal": 25000000,
    "title": "Senior iOS Developer"
},{
    "_id": "610f632b0112f1b4448d96d2",
    "applicant": 22,
    "company": "Senja",
    "currency": null,
    "end_sal": null,
    "exp_min": 1,
    "exp_opt": 3,
    "last_updated": null,
    "location": "Bandung",
    "start_sal": null,
    "title": "Web Developer"
},{
    "_id": "610f632b0112f1b4448d96d3",
    "applicant": 135,
    "company": "PT Code Development Indonesia",
    "currency": null,
    "end_sal": null,
    "exp_min": null,
    "exp_opt": null,
    "last_updated": 11,
    "location": "Jakarta",
    "start_sal": null,
    "title": "QA Engineer (Middle)"
},{
    "_id": "610f632b0112f1b4448d96d4",
    "applicant": 57,
    "company": "Rimba Ananta Vikasa Indonesia",
    "currency": null,
    "end_sal": null,
    "exp_min": 1,
    "exp_opt": 3,
    "last_updated": null,
    "location": "Jakarta",
    "start_sal": null,
    "title": "Fullstack Programmer"
},{
    "_id": "610f632b0112f1b4448d96d5",
    "applicant": 7,
    "company": "PT. Loyalty Program Indonesia",
    "currency": "IDR",
    "end_sal": 19000000,
    "exp_min": 5,
    "exp_opt": 10,
    "last_updated": 23,
    "location": "Jakarta",
    "start_sal": 15000000,
    "title": "Technical Lead"
},{
    "_id": "610f632b0112f1b4448d96d6",
    "applicant": 4,
    "company": "Pt Digital Agensi Nusantara",
    "currency": "IDR",
    "end_sal": 5000000,
    "exp_min": 1,
    "exp_opt": 3,
    "last_updated": 9,
    "location": "Bandung",
    "start_sal": 3000000,
    "title": "Backend Developer"
},{
    "_id": "610f632b0112f1b4448d96d7",
    "applicant": 20,
    "company": "Tix Id",
    "currency": "IDR",
    "end_sal": 10000000,
    "exp_min": 1,
    "exp_opt": 3,
    "last_updated": 4,
    "location": "Jakarta",
    "start_sal": 6000000,
    "title": "QA Engineer (Automation)"
},{
    "_id": "610f632b0112f1b4448d96d8",
    "applicant": 14,
    "company": "Chatbiz",
    "currency": null,
    "end_sal": null,
    "exp_min": 3,
    "exp_opt": 5,
    "last_updated": 20,
    "location": "Bandung",
    "start_sal": null,
    "title": "Frontend Developer"
},{
    "_id": "610f632b0112f1b4448d96d9",
    "applicant": 3,
    "company": "Stockbit",
    "currency": null,
    "end_sal": null,
    "exp_min": 3,
    "exp_opt": 5,
    "last_updated": 17,
    "location": "Jakarta",
    "start_sal": null,
    "title": "Senior Backend Engineer "
},{
    "_id": "610f632b0112f1b4448d96da",
    "applicant": 4,
    "company": "Nostratech",
    "currency": null,
    "end_sal": null,
    "exp_min": 1,
    "exp_opt": 3,
    "last_updated": 5,
    "location": "Jakarta",
    "start_sal": null,
    "title": "Mobile React-Native"
},{
    "_id": "610f632b0112f1b4448d96db",
    "applicant": 48,
    "company": "Pt. Dhana Jasa Konsultan",
    "currency": "IDR",
    "end_sal": 12000000,
    "exp_min": 5,
    "exp_opt": 10,
    "last_updated": 6,
    "location": "Jakarta",
    "start_sal": 10000000,
    "title": "Project Manager Infra & IT Security"
},{
    "_id": "610f632b0112f1b4448d96dc",
    "applicant": 95,
    "company": "PT. Teknologi Kode Indonesia",
    "currency": "IDR",
    "end_sal": 6500000,
    "exp_min": 1,
    "exp_opt": 3,
    "last_updated": 3,
    "location": "Yogyakarta",
    "start_sal": 5500000,
    "title": "System Analyst"
},{
    "_id": "610f632b0112f1b4448d96dd",
    "applicant": 22,
    "company": "Roho",
    "currency": null,
    "end_sal": null,
    "exp_min": 1,
    "exp_opt": 3,
    "last_updated": 30,
    "location": "Jakarta",
    "start_sal": null,
    "title": "Fullstack Developer (REMOTE)"
},{
    "_id": "610f632b0112f1b4448d96de",
    "applicant": 41,
    "company": "East Group",
    "currency": null,
    "end_sal": null,
    "exp_min": 1,
    "exp_opt": 3,
    "last_updated": 20,
    "location": "Jakarta",
    "start_sal": null,
    "title": "Wordpress Developer (REMOTE)"
},{
    "_id": "610f632b0112f1b4448d96df",
    "applicant": 57,
    "company": "OKANEMO",
    "currency": null,
    "end_sal": null,
    "exp_min": null,
    "exp_opt": null,
    "last_updated": null,
    "location": "Jakarta",
    "start_sal": null,
    "title": "Software Engineer Intern"
},{
    "_id": "610f632b0112f1b4448d96e0",
    "applicant": 64,
    "company": "Method Media",
    "currency": "IDR",
    "end_sal": 1600000000,
    "exp_min": 3,
    "exp_opt": 5,
    "last_updated": null,
    "location": "Jakarta",
    "start_sal": 1300000000,
    "title": "Front-End Developer"
},{
    "_id": "610f632b0112f1b4448d96e1",
    "applicant": 28,
    "company": "PT Dynamics Inovasi Solusindo",
    "currency": null,
    "end_sal": null,
    "exp_min": 0,
    "exp_opt": 1,
    "last_updated": 2,
    "location": "Tanah Abang, Jakarta",
    "start_sal": null,
    "title": "SOFTWARE DEVELOPER"
},{
    "_id": "610f632b0112f1b4448d96e2",
    "applicant": 3,
    "company": "PT Qtera Mandiri",
    "currency": "IDR",
    "end_sal": 5000000,
    "exp_min": 1,
    "exp_opt": 3,
    "last_updated": 12,
    "location": "Kelapa Gading, Jakarta",
    "start_sal": 3500000,
    "title": "FULLSTACK PROGRAMMER"
},{
    "_id": "610f632b0112f1b4448d96e3",
    "applicant": 77,
    "company": "Pt. Bukit Vista Nusantara",
    "currency": null,
    "end_sal": null,
    "exp_min": 0,
    "exp_opt": 1,
    "last_updated": 2,
    "location": "Jimbaran",
    "start_sal": null,
    "title": "Frontend Developer Intern"
},{
    "_id": "610f632b0112f1b4448d96e4",
    "applicant": 53,
    "company": "Geniebook Pte Ltd",
    "currency": "IDR",
    "end_sal": 10000000,
    "exp_min": 1,
    "exp_opt": 3,
    "last_updated": 1,
    "location": "Surabaya",
    "start_sal": 5000000,
    "title": "EdTech Kotlin Android Developer"
},{
    "_id": "610f632b0112f1b4448d96e5",
    "applicant": 72,
    "company": "Pt Linov Roket Prestasi",
    "currency": null,
    "end_sal": null,
    "exp_min": 1,
    "exp_opt": 3,
    "last_updated": 1,
    "location": "Jakarta",
    "start_sal": null,
    "title": "Software Tester / Quality Assurance (QA)"
},{
    "_id": "610f632b0112f1b4448d96e6",
    "applicant": 10,
    "company": "Nostratech",
    "currency": null,
    "end_sal": null,
    "exp_min": 3,
    "exp_opt": 5,
    "last_updated": 5,
    "location": "Jakarta",
    "start_sal": null,
    "title": "Web Frontend React.js Developer"
},{
    "_id": "610f632b0112f1b4448d96e7",
    "applicant": 22,
    "company": "Vouch SG Pte Ltd",
    "currency": null,
    "end_sal": null,
    "exp_min": 3,
    "exp_opt": 5,
    "last_updated": 18,
    "location": "Jakarta",
    "start_sal": null,
    "title": "Senior Software Developer (REMOTE)"
},{
    "_id": "610f632b0112f1b4448d96e8",
    "applicant": 216,
    "company": "PT. Barrans Global Mandiri",
    "currency": "IDR",
    "end_sal": 8000000,
    "exp_min": 1,
    "exp_opt": 3,
    "last_updated": 1,
    "location": "Bandung",
    "start_sal": 5000000,
    "title": "Quality Assurance"
},{
    "_id": "610f632b0112f1b4448d96e9",
    "applicant": 4,
    "company": "PT. Solusindo Global Digital",
    "currency": null,
    "end_sal": null,
    "exp_min": 1,
    "exp_opt": 3,
    "last_updated": 12,
    "location": "Jakarta",
    "start_sal": null,
    "title": "Junior Back End Microservice Developer"
},{
    "_id": "610f632b0112f1b4448d96ea",
    "applicant": 16,
    "company": "Pt Rangkaian Ide Dinamis",
    "currency": "IDR",
    "end_sal": 15000000,
    "exp_min": 3,
    "exp_opt": 5,
    "last_updated": 11,
    "location": "Jakarta",
    "start_sal": 7000000,
    "title": "Laravel Fullstack Developer"
},{
    "_id": "610f632b0112f1b4448d96eb",
    "applicant": 57,
    "company": "PT Nusantara Compnet Integrator",
    "currency": "IDR",
    "end_sal": 12000000,
    "exp_min": 1,
    "exp_opt": 3,
    "last_updated": 4,
    "location": "Jakarta",
    "start_sal": 6000000,
    "title": "System Analyst (Project Based)"
},{
    "_id": "610f632b0112f1b4448d96ec",
    "applicant": 111,
    "company": "PT. Bilna (Orami)",
    "currency": null,
    "end_sal": null,
    "exp_min": null,
    "exp_opt": null,
    "last_updated": 120,
    "location": "Tangerang",
    "start_sal": null,
    "title": "Middle QA"
},{
    "_id": "610f632b0112f1b4448d96ed",
    "applicant": 34,
    "company": "Waktukita.com",
    "currency": "IDR",
    "end_sal": 25000000,
    "exp_min": 3,
    "exp_opt": 5,
    "last_updated": 1,
    "location": "Jakarta",
    "start_sal": 20000000,
    "title": " Business Analyst (Software Development Company)"
},{
    "_id": "610f632b0112f1b4448d96ee",
    "applicant": 4,
    "company": "Pt. Dhana Jasa Konsultan",
    "currency": "IDR",
    "end_sal": 15000000,
    "exp_min": 5,
    "exp_opt": 10,
    "last_updated": 9,
    "location": "Jakarta",
    "start_sal": 9000000,
    "title": "Software Architect "
},{
    "_id": "610f632b0112f1b4448d96ef",
    "applicant": 5,
    "company": "Pt Kreasi Lebah Aktif",
    "currency": "IDR",
    "end_sal": 15000000,
    "exp_min": 1,
    "exp_opt": 3,
    "last_updated": 19,
    "location": "Jakarta",
    "start_sal": 7000000,
    "title": "iOS Engineer"
},{
    "_id": "610f632b0112f1b4448d96f0",
    "applicant": 6,
    "company": "Cause ID",
    "currency": "IDR",
    "end_sal": 7250000,
    "exp_min": 1,
    "exp_opt": 3,
    "last_updated": 6,
    "location": "Jakarta",
    "start_sal": 5000000,
    "title": "Mobile Application Developer (React Native)"
},{
    "_id": "610f632b0112f1b4448d96f1",
    "applicant": 17,
    "company": "Finku",
    "currency": "IDR",
    "end_sal": 5678,
    "exp_min": 1,
    "exp_opt": 3,
    "last_updated": 60,
    "location": "Jakarta",
    "start_sal": 1234,
    "title": "Frontend Engineer"
},{
    "_id": "610f632b0112f1b4448d96f2",
    "applicant": 1,
    "company": "PT. Asian Sigma Technology",
    "currency": "IDR",
    "end_sal": 14000000,
    "exp_min": 3,
    "exp_opt": 5,
    "last_updated": 20,
    "location": "Jakarta",
    "start_sal": 12000000,
    "title": ".Net Developer"
},{
    "_id": "610f632b0112f1b4448d96f3",
    "applicant": 11,
    "company": "Qubisa",
    "currency": null,
    "end_sal": null,
    "exp_min": 1,
    "exp_opt": 3,
    "last_updated": 17,
    "location": "Jakarta",
    "start_sal": null,
    "title": "Back End Developer"
},{
    "_id": "610f632b0112f1b4448d96f4",
    "applicant": 3,
    "company": "Pt Prisma Harapan",
    "currency": null,
    "end_sal": null,
    "exp_min": 1,
    "exp_opt": 3,
    "last_updated": 2,
    "location": "Kebon Jeruk, Jakarta",
    "start_sal": null,
    "title": "Junior Full-stack Developer"
},{
    "_id": "610f632b0112f1b4448d96f5",
    "applicant": 195,
    "company": "Company Confidential",
    "currency": "IDR",
    "end_sal": 50000000,
    "exp_min": 3,
    "exp_opt": 5,
    "last_updated": null,
    "location": "Jakarta",
    "start_sal": 40000000,
    "title": "VP of Engineering"
},{
    "_id": "610f632b0112f1b4448d96f6",
    "applicant": 181,
    "company": "Hartono Elektronika",
    "currency": "IDR",
    "end_sal": 8000000,
    "exp_min": 1,
    "exp_opt": 3,
    "last_updated": null,
    "location": "Surabaya",
    "start_sal": 5000000,
    "title": "Business Intelligence Analyst"
},{
    "_id": "610f632b0112f1b4448d96f7",
    "applicant": 31,
    "company": "Latis Education",
    "currency": "IDR",
    "end_sal": 6500000,
    "exp_min": 1,
    "exp_opt": 3,
    "last_updated": 1,
    "location": "Depok",
    "start_sal": 5000000,
    "title": "IT Developer"
},{
    "_id": "610f632b0112f1b4448d96f8",
    "applicant": 13,
    "company": "itemku",
    "currency": "IDR",
    "end_sal": 13000000,
    "exp_min": 0,
    "exp_opt": 1,
    "last_updated": 1,
    "location": "Grogol Petamburan, Jakarta",
    "start_sal": 6500000,
    "title": "Software Engineer (Fresh Graduate)"
},{
    "_id": "610f632b0112f1b4448d96f9",
    "applicant": 15,
    "company": "PT Astronacci International",
    "currency": null,
    "end_sal": null,
    "exp_min": 1,
    "exp_opt": 3,
    "last_updated": 13,
    "location": "Kelapa Gading, Jakarta",
    "start_sal": null,
    "title": "Mobile App Developer"
},{
    "_id": "610f632b0112f1b4448d96fa",
    "applicant": 16,
    "company": "Pt Platinumetrix Global Inovasi",
    "currency": "IDR",
    "end_sal": 13000000,
    "exp_min": 3,
    "exp_opt": 5,
    "last_updated": 30,
    "location": "Jakarta",
    "start_sal": 6500000,
    "title": "Scrum Master"
},{
    "_id": "610f632b0112f1b4448d96fb",
    "applicant": 32,
    "company": "Cloud Thought LTD",
    "currency": null,
    "end_sal": null,
    "exp_min": 1,
    "exp_opt": 3,
    "last_updated": 27,
    "location": "Jakarta",
    "start_sal": null,
    "title": "Fullstack Developer"
},{
    "_id": "610f632b0112f1b4448d96fc",
    "applicant": 11,
    "company": "Pt Enam Samudra Teknologi",
    "currency": "IDR",
    "end_sal": 10000000,
    "exp_min": 1,
    "exp_opt": 3,
    "last_updated": 20,
    "location": "Jakarta",
    "start_sal": 7000000,
    "title": "FLUTTER ENGINEER"
},{
    "_id": "610f632b0112f1b4448d96fd",
    "applicant": 97,
    "company": "PT. Asian Sigma Technology",
    "currency": "IDR",
    "end_sal": 11000000,
    "exp_min": 1,
    "exp_opt": 3,
    "last_updated": 3,
    "location": "Mampang Prapatan, Jakarta",
    "start_sal": 6000000,
    "title": "Front End Developer"
},{
    "_id": "610f632b0112f1b4448d96fe",
    "applicant": 13,
    "company": "PT Widya Inovasi Indonesia",
    "currency": "IDR",
    "end_sal": 4000000,
    "exp_min": 1,
    "exp_opt": 3,
    "last_updated": 60,
    "location": "Yogyakarta",
    "start_sal": 3500000,
    "title": "Fullstack "
},{
    "_id": "610f632b0112f1b4448d96ff",
    "applicant": 51,
    "company": "PT. Prodata Sistem Teknologi",
    "currency": "IDR",
    "end_sal": 6000000,
    "exp_min": 1,
    "exp_opt": 3,
    "last_updated": 1,
    "location": "Jakarta",
    "start_sal": 4000000,
    "title": "IT Network & System Engineer"
},{
    "_id": "610f632b0112f1b4448d9700",
    "applicant": 1,
    "company": "Digital Envision",
    "currency": "IDR",
    "end_sal": 8000000,
    "exp_min": 1,
    "exp_opt": 3,
    "last_updated": 12,
    "location": "Semarang",
    "start_sal": 3000000,
    "title": "Fullstack Developer"
},{
    "_id": "610f632b0112f1b4448d9701",
    "applicant": 58,
    "company": "Cloud Comrade",
    "currency": null,
    "end_sal": null,
    "exp_min": 1,
    "exp_opt": 3,
    "last_updated": 18,
    "location": "Bandung",
    "start_sal": null,
    "title": "Junior Cloud Engineer "
},{
    "_id": "610f632b0112f1b4448d9702",
    "applicant": 83,
    "company": "Arvis",
    "currency": "IDR",
    "end_sal": 10000000,
    "exp_min": 1,
    "exp_opt": 3,
    "last_updated": 2,
    "location": "Jakarta",
    "start_sal": 5500000,
    "title": "Backend Engineer"
},{
    "_id": "610f632b0112f1b4448d9703",
    "applicant": 2,
    "company": "Waktukita.com",
    "currency": "IDR",
    "end_sal": 20000000,
    "exp_min": 3,
    "exp_opt": 5,
    "last_updated": 27,
    "location": "Jakarta",
    "start_sal": 10000000,
    "title": "Ruby Developer (Software Development Company)"
},{
    "_id": "610f632b0112f1b4448d9704",
    "applicant": 17,
    "company": "Waktukita.com",
    "currency": "IDR",
    "end_sal": 20000000,
    "exp_min": 3,
    "exp_opt": 5,
    "last_updated": 30,
    "location": "Jakarta",
    "start_sal": 10000000,
    "title": " Front-end Developer (Software Development Company)"
},{
    "_id": "610f632b0112f1b4448d9705",
    "applicant": 2,
    "company": "Waktukita.com",
    "currency": "IDR",
    "end_sal": 20000000,
    "exp_min": 3,
    "exp_opt": 5,
    "last_updated": 27,
    "location": "Jakarta",
    "start_sal": 10000000,
    "title": "ETL Developer (Software Development Service)"
},{
    "_id": "610f632b0112f1b4448d9706",
    "applicant": 15,
    "company": "Waktukita.com",
    "currency": "IDR",
    "end_sal": 20000000,
    "exp_min": 3,
    "exp_opt": 5,
    "last_updated": 30,
    "location": "Jakarta",
    "start_sal": 10000000,
    "title": "Back-end Developer (Software Development Service)"
},{
    "_id": "610f632b0112f1b4448d9707",
    "applicant": 4,
    "company": "Waktukita.com",
    "currency": "IDR",
    "end_sal": 20000000,
    "exp_min": 3,
    "exp_opt": 5,
    "last_updated": 26,
    "location": "Jakarta",
    "start_sal": 10000000,
    "title": "Front-end Developer (Software Development Service)"
},{
    "_id": "610f632b0112f1b4448d9708",
    "applicant": 39,
    "company": "Trakomatic Pte Ltd",
    "currency": null,
    "end_sal": null,
    "exp_min": 3,
    "exp_opt": 5,
    "last_updated": 10,
    "location": "Jakarta",
    "start_sal": null,
    "title": "Web Software Engineer (REMOTE)"
},{
    "_id": "610f632b0112f1b4448d9709",
    "applicant": 49,
    "company": "PT Verita Informatika",
    "currency": "IDR",
    "end_sal": 30000000,
    "exp_min": 3,
    "exp_opt": 5,
    "last_updated": 5,
    "location": "Tanah Abang, Jakarta",
    "start_sal": 15000000,
    "title": "Android Developer"
},{
    "_id": "610f632b0112f1b4448d970a",
    "applicant": 11,
    "company": "Terralogiq",
    "currency": "IDR",
    "end_sal": 13000000,
    "exp_min": 5,
    "exp_opt": 10,
    "last_updated": 18,
    "location": "Kemang",
    "start_sal": 10000000,
    "title": "Full Stack Developer"
},{
    "_id": "610f632b0112f1b4448d970b",
    "applicant": 6,
    "company": "Refactory.id",
    "currency": null,
    "end_sal": null,
    "exp_min": 0,
    "exp_opt": 1,
    "last_updated": 18,
    "location": "Yogyakarta",
    "start_sal": null,
    "title": "Junior Golang Engineer"
},{
    "_id": "610f632b0112f1b4448d970c",
    "applicant": 42,
    "company": "Bridge Note Indonesia",
    "currency": "IDR",
    "end_sal": 15000000,
    "exp_min": 1,
    "exp_opt": 3,
    "last_updated": 1,
    "location": "Jakarta",
    "start_sal": 7500000,
    "title": "UI/UX Designer"
},{
    "_id": "610f632b0112f1b4448d970d",
    "applicant": 38,
    "company": "PT Wahana Duta Jaya Rucika",
    "currency": null,
    "end_sal": null,
    "exp_min": 1,
    "exp_opt": 3,
    "last_updated": 13,
    "location": "Jakarta",
    "start_sal": null,
    "title": "Application Officer"
},{
    "_id": "610f632b0112f1b4448d970e",
    "applicant": 348,
    "company": "Pt Platinumetrix Global Inovasi",
    "currency": "IDR",
    "end_sal": 15000000,
    "exp_min": 1,
    "exp_opt": 3,
    "last_updated": null,
    "location": "Jakarta",
    "start_sal": 7500000,
    "title": "IT Business Analyst"
},{
    "_id": "610f632b0112f1b4448d970f",
    "applicant": 42,
    "company": "Takalab",
    "currency": "IDR",
    "end_sal": 3200000,
    "exp_min": null,
    "exp_opt": null,
    "last_updated": 1,
    "location": "Mampang Prapatan, Jakarta",
    "start_sal": 3000000,
    "title": "Front-End Developer - Intern"
},{
    "_id": "610f632b0112f1b4448d9710",
    "applicant": 63,
    "company": "Glints",
    "currency": null,
    "end_sal": null,
    "exp_min": 1,
    "exp_opt": 3,
    "last_updated": 1,
    "location": "Jakarta",
    "start_sal": null,
    "title": "Software QA Engineer"
},{
    "_id": "610f632b0112f1b4448d9711",
    "applicant": 133,
    "company": "mHealthBank",
    "currency": null,
    "end_sal": null,
    "exp_min": 3,
    "exp_opt": 5,
    "last_updated": 120,
    "location": "Jakarta",
    "start_sal": null,
    "title": "Senior BACKEND .NET Engineer"
},{
    "_id": "610f632b0112f1b4448d9712",
    "applicant": 346,
    "company": "Cv. Konsultan Teknologi Indonesia",
    "currency": "IDR",
    "end_sal": 12000000,
    "exp_min": 1,
    "exp_opt": 3,
    "last_updated": 1,
    "location": "Jakarta",
    "start_sal": 10000000,
    "title": "Quality Assurance"
},{
    "_id": "610f632b0112f1b4448d9713",
    "applicant": 67,
    "company": "Rimba Ananta Vikasa Indonesia",
    "currency": null,
    "end_sal": null,
    "exp_min": 1,
    "exp_opt": 3,
    "last_updated": 1,
    "location": "Semarang",
    "start_sal": null,
    "title": "Back End Programmer"
},{
    "_id": "610f632b0112f1b4448d9714",
    "applicant": 176,
    "company": "Toyota Astra Financial(taf)",
    "currency": null,
    "end_sal": null,
    "exp_min": 0,
    "exp_opt": 1,
    "last_updated": 5,
    "location": "Jakarta",
    "start_sal": null,
    "title": "IT Analyst"
},{
    "_id": "610f632b0112f1b4448d9715",
    "applicant": 115,
    "company": "PT Qtasnim Digital Teknologi",
    "currency": null,
    "end_sal": null,
    "exp_min": 1,
    "exp_opt": 3,
    "last_updated": null,
    "location": "Bandung",
    "start_sal": null,
    "title": "IT Technical Support"
},{
    "_id": "610f632b0112f1b4448d9716",
    "applicant": 43,
    "company": "Emtrade",
    "currency": null,
    "end_sal": null,
    "exp_min": 1,
    "exp_opt": 3,
    "last_updated": null,
    "location": "Jakarta",
    "start_sal": null,
    "title": "Front End Developer"
},{
    "_id": "610f632b0112f1b4448d9717",
    "applicant": 73,
    "company": "Hartono Elektronika",
    "currency": "IDR",
    "end_sal": 6000000,
    "exp_min": 0,
    "exp_opt": 1,
    "last_updated": 2,
    "location": "Surabaya",
    "start_sal": 4000000,
    "title": "Full Stack Web Developer"
},{
    "_id": "610f632b0112f1b4448d9718",
    "applicant": 33,
    "company": "Accusentry",
    "currency": "IDR",
    "end_sal": 8000000,
    "exp_min": null,
    "exp_opt": null,
    "last_updated": 1,
    "location": "Jakarta",
    "start_sal": 7000000,
    "title": "Software Developer"
},{
    "_id": "610f632b0112f1b4448d9719",
    "applicant": 24,
    "company": "Pt Solusi Teknologi Niaga",
    "currency": null,
    "end_sal": null,
    "exp_min": 1,
    "exp_opt": 3,
    "last_updated": 2,
    "location": "Jakarta",
    "start_sal": null,
    "title": "QA Engineer (Software Development Engineer in Test)"
},{
    "_id": "610f632b0112f1b4448d971a",
    "applicant": 518,
    "company": "PT Stampindo Lancar Jaya",
    "currency": "IDR",
    "end_sal": 10000000,
    "exp_min": null,
    "exp_opt": null,
    "last_updated": 1,
    "location": "Jakarta",
    "start_sal": 5000000,
    "title": "Junior Software Developer"
},{
    "_id": "610f632b0112f1b4448d971b",
    "applicant": 20,
    "company": "Pt Knitto Tekstil Indonesia",
    "currency": "IDR",
    "end_sal": 6000000,
    "exp_min": 1,
    "exp_opt": 3,
    "last_updated": 1,
    "location": "Bandung",
    "start_sal": 4500000,
    "title": "IT Programmer"
},{
    "_id": "610f632b0112f1b4448d971c",
    "applicant": 53,
    "company": "Pt Enam Samudra Teknologi",
    "currency": "IDR",
    "end_sal": 11000000,
    "exp_min": 1,
    "exp_opt": 3,
    "last_updated": null,
    "location": "Jakarta",
    "start_sal": 8000000,
    "title": "QA Automation"
},{
    "_id": "610f632b0112f1b4448d971d",
    "applicant": 44,
    "company": "Movus Technologies",
    "currency": null,
    "end_sal": null,
    "exp_min": 1,
    "exp_opt": 3,
    "last_updated": 1,
    "location": "Jakarta",
    "start_sal": null,
    "title": "The First QA Tester"
},{
    "_id": "610f632b0112f1b4448d971e",
    "applicant": 108,
    "company": "Takalab",
    "currency": "IDR",
    "end_sal": 12000000,
    "exp_min": 1,
    "exp_opt": 3,
    "last_updated": 1,
    "location": "Mampang Prapatan, Jakarta",
    "start_sal": 6000000,
    "title": "Backend Developer (Junior - Middle)"
},{
    "_id": "610f632b0112f1b4448d971f",
    "applicant": 38,
    "company": "Smartlegal.id",
    "currency": null,
    "end_sal": null,
    "exp_min": null,
    "exp_opt": null,
    "last_updated": 1,
    "location": "Malang",
    "start_sal": null,
    "title": "CREATIVE DESIGN "
},{
    "_id": "610f632b0112f1b4448d9720",
    "applicant": 30,
    "company": "Pt Platinumetrix Global Inovasi",
    "currency": "IDR",
    "end_sal": 13000000,
    "exp_min": 1,
    "exp_opt": 3,
    "last_updated": null,
    "location": "Jakarta",
    "start_sal": 6500000,
    "title": "React Native Developer"
},{
    "_id": "610f632b0112f1b4448d9721",
    "applicant": 50,
    "company": "MNC Group",
    "currency": null,
    "end_sal": null,
    "exp_min": 1,
    "exp_opt": 3,
    "last_updated": 2,
    "location": "Menteng, Jakarta",
    "start_sal": null,
    "title": "UI/UX Developer"
},{
    "_id": "610f632b0112f1b4448d9722",
    "applicant": 11,
    "company": "Pijar Indonesia",
    "currency": "IDR",
    "end_sal": 7000000,
    "exp_min": 1,
    "exp_opt": 3,
    "last_updated": 6,
    "location": "Tebet, Jakarta",
    "start_sal": 6000000,
    "title": "Mobile Developer (React Native)"
},{
    "_id": "610f632b0112f1b4448d9723",
    "applicant": 61,
    "company": "Waktukita.com",
    "currency": "IDR",
    "end_sal": 20000000,
    "exp_min": 3,
    "exp_opt": 5,
    "last_updated": 2,
    "location": "Jakarta",
    "start_sal": 10000000,
    "title": "Software Tester (Software Development Company)"
},{
    "_id": "610f632b0112f1b4448d9724",
    "applicant": 177,
    "company": "Glints Indonesia",
    "currency": "IDR",
    "end_sal": 50000000,
    "exp_min": null,
    "exp_opt": null,
    "last_updated": 2,
    "location": "Jakarta",
    "start_sal": 20000000,
    "title": "Mobile Engineer (Flutter) "
},{
    "_id": "610f632b0112f1b4448d9725",
    "applicant": 11,
    "company": "PT. Asian Sigma Technology",
    "currency": "IDR",
    "end_sal": 12000000,
    "exp_min": 1,
    "exp_opt": 3,
    "last_updated": 10,
    "location": "Abang",
    "start_sal": 5000000,
    "title": "Telco - React JS Developer"
},{
    "_id": "610f632b0112f1b4448d9726",
    "applicant": 15,
    "company": "Renos",
    "currency": null,
    "end_sal": null,
    "exp_min": 3,
    "exp_opt": 5,
    "last_updated": 4,
    "location": "Jakarta",
    "start_sal": null,
    "title": "Front End Developer"
},{
    "_id": "610f632b0112f1b4448d9727",
    "applicant": 20,
    "company": "PT Qtera Mandiri",
    "currency": "IDR",
    "end_sal": 5000000,
    "exp_min": 0,
    "exp_opt": 1,
    "last_updated": null,
    "location": "Kelapa Gading, Jakarta",
    "start_sal": 3500000,
    "title": "PROGRAMMER ARDUINO"
},{
    "_id": "610f632b0112f1b4448d9728",
    "applicant": 31,
    "company": "Pt Kreator Solusi Informasi",
    "currency": "IDR",
    "end_sal": 5500000,
    "exp_min": null,
    "exp_opt": null,
    "last_updated": 1,
    "location": "Surabaya",
    "start_sal": 4500000,
    "title": "Staff Programmer"
},{
    "_id": "610f632b0112f1b4448d9729",
    "applicant": 51,
    "company": "South East Islands Group",
    "currency": "IDR",
    "end_sal": 15000000,
    "exp_min": null,
    "exp_opt": null,
    "last_updated": null,
    "location": "Jakarta",
    "start_sal": 9000000,
    "title": "Full Stack Developer (Open for Fresh Grads)"
},{
    "_id": "610f632b0112f1b4448d972a",
    "applicant": 17,
    "company": "Pt. Ewide Indonesia",
    "currency": "IDR",
    "end_sal": 30000000,
    "exp_min": 5,
    "exp_opt": 10,
    "last_updated": 18,
    "location": "SCBD, Jakarta",
    "start_sal": 10000000,
    "title": "Frontend Developer"
},{
    "_id": "610f632b0112f1b4448d972b",
    "applicant": 26,
    "company": "Vi8e Interactive Pte. Ltd.",
    "currency": "IDR",
    "end_sal": 10000000,
    "exp_min": 1,
    "exp_opt": 3,
    "last_updated": null,
    "location": "Surabaya",
    "start_sal": 7000000,
    "title": "Senior PHP Developer"
},{
    "_id": "610f632b0112f1b4448d972c",
    "applicant": 33,
    "company": "Nostratech",
    "currency": null,
    "end_sal": null,
    "exp_min": null,
    "exp_opt": null,
    "last_updated": 30,
    "location": "Jakarta",
    "start_sal": null,
    "title": "Frontend Engineer (Vue.JS)"
},{
    "_id": "610f632b0112f1b4448d972d",
    "applicant": 8,
    "company": "Pt Majapahit Teknologi Nusantara",
    "currency": "IDR",
    "end_sal": 7000000,
    "exp_min": 1,
    "exp_opt": 3,
    "last_updated": 6,
    "location": "Cakung, Jakarta",
    "start_sal": 4500000,
    "title": "React Js"
},{
    "_id": "610f632b0112f1b4448d972e",
    "applicant": 48,
    "company": "Pt Linov Roket Prestasi",
    "currency": "IDR",
    "end_sal": 9000000,
    "exp_min": 1,
    "exp_opt": 3,
    "last_updated": 2,
    "location": "Tebet, Jakarta",
    "start_sal": 5000000,
    "title": "Android Developer"
},{
    "_id": "610f632b0112f1b4448d972f",
    "applicant": 11,
    "company": "PT Supertone (SPC)",
    "currency": "IDR",
    "end_sal": 15000000,
    "exp_min": 1,
    "exp_opt": 3,
    "last_updated": 16,
    "location": "Jakarta",
    "start_sal": 8000000,
    "title": "HARDWARE & SOFTWARE ENGINEER"
},{
    "_id": "610f632b0112f1b4448d9730",
    "applicant": 15,
    "company": "Cv. Konsultan Teknologi Indonesia",
    "currency": "IDR",
    "end_sal": 15000000,
    "exp_min": 1,
    "exp_opt": 3,
    "last_updated": 18,
    "location": "Jakarta",
    "start_sal": 10000000,
    "title": "Back End Developer"
},{
    "_id": "610f632b0112f1b4448d9731",
    "applicant": 11,
    "company": "PT Qtera Mandiri",
    "currency": "IDR",
    "end_sal": 5000000,
    "exp_min": 1,
    "exp_opt": 3,
    "last_updated": 6,
    "location": "Kelapa Gading, Jakarta",
    "start_sal": 3500000,
    "title": "FRONT & BACK END PROGRAMMER"
},{
    "_id": "610f632b0112f1b4448d9732",
    "applicant": 37,
    "company": "PT. Asian Sigma Technology",
    "currency": "IDR",
    "end_sal": 10000000,
    "exp_min": 3,
    "exp_opt": 5,
    "last_updated": 13,
    "location": "Jakarta",
    "start_sal": 10000000,
    "title": "PHP Developer (Laravel)"
},{
    "_id": "610f632b0112f1b4448d9733",
    "applicant": 44,
    "company": "MNC Group",
    "currency": null,
    "end_sal": null,
    "exp_min": 3,
    "exp_opt": 5,
    "last_updated": 2,
    "location": "Menteng, Jakarta",
    "start_sal": null,
    "title": "QA/QC Engineer"
},{
    "_id": "610f632b0112f1b4448d9734",
    "applicant": 104,
    "company": "PT Nusantara Compnet Integrator",
    "currency": "IDR",
    "end_sal": 12000000,
    "exp_min": 1,
    "exp_opt": 3,
    "last_updated": 2,
    "location": "Jakarta",
    "start_sal": 6000000,
    "title": "System Analyst (Project Based)"
},{
    "_id": "610f632b0112f1b4448d9735",
    "applicant": 7,
    "company": "Studycle",
    "currency": "IDR",
    "end_sal": 12000000,
    "exp_min": 3,
    "exp_opt": 5,
    "last_updated": 14,
    "location": "Bandung",
    "start_sal": 7000000,
    "title": "Senior Software Engineer"
},{
    "_id": "610f632b0112f1b4448d9736",
    "applicant": 8,
    "company": "PT Mplus Solusi Perdana",
    "currency": "IDR",
    "end_sal": 10000000,
    "exp_min": 1,
    "exp_opt": 3,
    "last_updated": 5,
    "location": "Jakarta",
    "start_sal": 6000000,
    "title": "Java Script"
},{
    "_id": "610f632b0112f1b4448d9737",
    "applicant": 89,
    "company": "Jublia",
    "currency": "IDR",
    "end_sal": 20000000,
    "exp_min": 1,
    "exp_opt": 3,
    "last_updated": 20,
    "location": "Tangerang",
    "start_sal": 5000000,
    "title": "Front End Engineer (VueJS)"
},{
    "_id": "610f632b0112f1b4448d9738",
    "applicant": 223,
    "company": "PT. Access Mobile Indonesia",
    "currency": "IDR",
    "end_sal": 20000000,
    "exp_min": 1,
    "exp_opt": 3,
    "last_updated": 4,
    "location": "Jakarta",
    "start_sal": 10000000,
    "title": "Front-End Developer"
},{
    "_id": "610f632b0112f1b4448d9739",
    "applicant": 148,
    "company": "PT. Access Mobile Indonesia",
    "currency": "IDR",
    "end_sal": 20000000,
    "exp_min": 1,
    "exp_opt": 3,
    "last_updated": 3,
    "location": "Jakarta",
    "start_sal": 10000000,
    "title": "Back-End Developer"
},{
    "_id": "610f632b0112f1b4448d973a",
    "applicant": 324,
    "company": "Matoa Indonesia",
    "currency": null,
    "end_sal": null,
    "exp_min": 1,
    "exp_opt": 3,
    "last_updated": null,
    "location": "Bandung",
    "start_sal": null,
    "title": "IT Staff "
},{
    "_id": "610f632b0112f1b4448d973b",
    "applicant": 19,
    "company": "mHealthBank",
    "currency": null,
    "end_sal": null,
    "exp_min": 3,
    "exp_opt": 5,
    "last_updated": 30,
    "location": "Jakarta",
    "start_sal": null,
    "title": "QA Test (Automation) "
},{
    "_id": "610f632b0112f1b4448d973c",
    "applicant": 5,
    "company": "Hzn",
    "currency": "IDR",
    "end_sal": 12000000,
    "exp_min": 1,
    "exp_opt": 3,
    "last_updated": 6,
    "location": "Tangerang",
    "start_sal": 7000000,
    "title": "Software Development Engineer I - Web"
},{
    "_id": "610f632b0112f1b4448d973d",
    "applicant": 172,
    "company": "Aliansi Koin",
    "currency": "IDR",
    "end_sal": 6000000,
    "exp_min": 1,
    "exp_opt": 3,
    "last_updated": 2,
    "location": "Jakarta",
    "start_sal": 4500000,
    "title": "Junior Web Engineer"
},{
    "_id": "610f632b0112f1b4448d973e",
    "applicant": 15,
    "company": "Studycle",
    "currency": "IDR",
    "end_sal": 7000000,
    "exp_min": 1,
    "exp_opt": 3,
    "last_updated": 30,
    "location": "Bandung",
    "start_sal": 5000000,
    "title": "Fullstack Developer"
},{
    "_id": "610f632b0112f1b4448d973f",
    "applicant": 141,
    "company": "PT. Folarium Innotek Indonesia",
    "currency": null,
    "end_sal": null,
    "exp_min": 0,
    "exp_opt": 1,
    "last_updated": null,
    "location": "Jakarta",
    "start_sal": null,
    "title": "Software QA Test Intern"
},{
    "_id": "610f632b0112f1b4448d9740",
    "applicant": 5,
    "company": "Pintu",
    "currency": "IDR",
    "end_sal": 5678,
    "exp_min": 1,
    "exp_opt": 3,
    "last_updated": 6,
    "location": "Jakarta",
    "start_sal": 1234,
    "title": "Senior Backend Engineer"
},{
    "_id": "610f632b0112f1b4448d9741",
    "applicant": 3,
    "company": "Tix Id",
    "currency": "IDR",
    "end_sal": 25000000,
    "exp_min": 3,
    "exp_opt": 5,
    "last_updated": 4,
    "location": "Jakarta",
    "start_sal": 15000000,
    "title": "Senior Backend Developer"
},{
    "_id": "610f632b0112f1b4448d9742",
    "applicant": 137,
    "company": "Imv",
    "currency": "IDR",
    "end_sal": 15000000,
    "exp_min": 3,
    "exp_opt": 5,
    "last_updated": 1,
    "location": "Tangerang",
    "start_sal": 7500000,
    "title": "Frontend Web Developer"
},{
    "_id": "610f632b0112f1b4448d9743",
    "applicant": 58,
    "company": "Klinik Utama & Laboratorium Cmi",
    "currency": "IDR",
    "end_sal": 5000000,
    "exp_min": 1,
    "exp_opt": 3,
    "last_updated": 1,
    "location": "Bandung",
    "start_sal": 4000000,
    "title": "Security Network "
},{
    "_id": "610f632b0112f1b4448d9744",
    "applicant": 8,
    "company": "Prosa.ai",
    "currency": "IDR",
    "end_sal": 15000000,
    "exp_min": 1,
    "exp_opt": 3,
    "last_updated": 7,
    "location": "Bandung",
    "start_sal": 8000000,
    "title": "Full Stack Engineer"
},{
    "_id": "610f632b0112f1b4448d9745",
    "applicant": 25,
    "company": "Jakarta Web Solution",
    "currency": "IDR",
    "end_sal": 25000000,
    "exp_min": 3,
    "exp_opt": 5,
    "last_updated": 12,
    "location": "Jakarta",
    "start_sal": 15000000,
    "title": "Software Engineer (manage Services)"
},{
    "_id": "610f632b0112f1b4448d9746",
    "applicant": 36,
    "company": "Ent-vision",
    "currency": "IDR",
    "end_sal": 15000000,
    "exp_min": 3,
    "exp_opt": 5,
    "last_updated": 1,
    "location": "Jakarta",
    "start_sal": 10000000,
    "title": "Full-stack Developer (REMOTE)"
},{
    "_id": "610f632b0112f1b4448d9747",
    "applicant": 40,
    "company": "Waktukita.com",
    "currency": "IDR",
    "end_sal": 25000000,
    "exp_min": 5,
    "exp_opt": 10,
    "last_updated": 2,
    "location": "Jakarta",
    "start_sal": 20000000,
    "title": "IT Project Manager / Scrum Master (Software Development Company)"
},{
    "_id": "610f632b0112f1b4448d9748",
    "applicant": 37,
    "company": "Klinik Utama & Laboratorium Cmi",
    "currency": "IDR",
    "end_sal": 4500000,
    "exp_min": 1,
    "exp_opt": 3,
    "last_updated": 1,
    "location": "Bandung",
    "start_sal": 3500000,
    "title": "Programmer"
},{
    "_id": "610f632b0112f1b4448d9749",
    "applicant": 14,
    "company": "PT Indopasifik Teknologi Medika Indonesia",
    "currency": "IDR",
    "end_sal": 12000000,
    "exp_min": 1,
    "exp_opt": 3,
    "last_updated": 20,
    "location": "Jakarta",
    "start_sal": 8000000,
    "title": "Back-End Engineer"
},{
    "_id": "610f632b0112f1b4448d974a",
    "applicant": 158,
    "company": "Autovice.id",
    "currency": "IDR",
    "end_sal": 10000000,
    "exp_min": 1,
    "exp_opt": 3,
    "last_updated": 1,
    "location": "Tangerang",
    "start_sal": 5000000,
    "title": "Back End Developer"
},{
    "_id": "610f632b0112f1b4448d974b",
    "applicant": 5,
    "company": "Senja",
    "currency": "IDR",
    "end_sal": 20000000,
    "exp_min": 3,
    "exp_opt": 5,
    "last_updated": 5,
    "location": "Bandung",
    "start_sal": 15000000,
    "title": "Mid/Senior Frontend Developer"
},{
    "_id": "610f632b0112f1b4448d974c",
    "applicant": 11,
    "company": "PT Qtera Mandiri",
    "currency": "IDR",
    "end_sal": 5000000,
    "exp_min": 1,
    "exp_opt": 3,
    "last_updated": 13,
    "location": "Kelapa Gading, Jakarta",
    "start_sal": 3500000,
    "title": "IT MOBILE PROGRAMMER"
},{
    "_id": "610f632b0112f1b4448d974d",
    "applicant": 19,
    "company": "Mayar",
    "currency": null,
    "end_sal": null,
    "exp_min": 1,
    "exp_opt": 3,
    "last_updated": 4,
    "location": "Bandung",
    "start_sal": null,
    "title": "Frontend Engineer (React/JS)  - REMOTE"
},{
    "_id": "610f632b0112f1b4448d974e",
    "applicant": 13,
    "company": "Bridge Note Indonesia",
    "currency": "IDR",
    "end_sal": 20000000,
    "exp_min": 3,
    "exp_opt": 5,
    "last_updated": 5,
    "location": "Jakarta",
    "start_sal": 10000000,
    "title": "Web Programmer (Software Developer Engineer)"
},{
    "_id": "610f632b0112f1b4448d974f",
    "applicant": 16,
    "company": "Coconut Lab Pte Ltd",
    "currency": null,
    "end_sal": null,
    "exp_min": 3,
    "exp_opt": 5,
    "last_updated": 6,
    "location": "Jakarta",
    "start_sal": null,
    "title": "Quality Assurance (QA) / Test Engineer"
},{
    "_id": "610f632b0112f1b4448d9750",
    "applicant": 31,
    "company": "My Hunter",
    "currency": "IDR",
    "end_sal": 10000000,
    "exp_min": 1,
    "exp_opt": 3,
    "last_updated": 1,
    "location": "Menteng, Jakarta",
    "start_sal": 5000000,
    "title": "Backend Developer (Java)"
},{
    "_id": "610f632b0112f1b4448d9751",
    "applicant": 13,
    "company": "Pt Enam Samudra Teknologi",
    "currency": "IDR",
    "end_sal": 13000000,
    "exp_min": 3,
    "exp_opt": 5,
    "last_updated": 23,
    "location": "Kuningan, Jakarta",
    "start_sal": 8000000,
    "title": "BACKEND ENGINEER"
},{
    "_id": "610f632b0112f1b4448d9752",
    "applicant": 18,
    "company": "Avana Indonesia",
    "currency": "IDR",
    "end_sal": 12000000,
    "exp_min": 3,
    "exp_opt": 5,
    "last_updated": 23,
    "location": "Bandung",
    "start_sal": 8000000,
    "title": "Software Quality Assurance"
},{
    "_id": "610f632b0112f1b4448d9753",
    "applicant": 87,
    "company": "Geniebook Pte Ltd",
    "currency": "IDR",
    "end_sal": 10000000,
    "exp_min": 1,
    "exp_opt": 3,
    "last_updated": 5,
    "location": "Surabaya",
    "start_sal": 7000000,
    "title": "EdTech Data Engineer"
},{
    "_id": "610f632b0112f1b4448d9754",
    "applicant": 14,
    "company": "ProSpace Pte Ltd",
    "currency": "SGD",
    "end_sal": 1600,
    "exp_min": 3,
    "exp_opt": 5,
    "last_updated": 20,
    "location": "Batam",
    "start_sal": 1000,
    "title": "iOS Engineer"
},{
    "_id": "610f632b0112f1b4448d9755",
    "applicant": 23,
    "company": "Resync Technologies",
    "currency": "IDR",
    "end_sal": 20000000,
    "exp_min": 5,
    "exp_opt": 10,
    "last_updated": 2,
    "location": "Jakarta",
    "start_sal": 0,
    "title": "Remote Senior Full Stack Developer focused on FrontEnd"
},{
    "_id": "610f632b0112f1b4448d9756",
    "applicant": 11,
    "company": "Pt Platinumetrix Global Inovasi",
    "currency": "IDR",
    "end_sal": 15000000,
    "exp_min": 3,
    "exp_opt": 5,
    "last_updated": 18,
    "location": "Jakarta",
    "start_sal": 7500000,
    "title": "Full Stack Developer"
},{
    "_id": "610f632b0112f1b4448d9757",
    "applicant": 116,
    "company": "Coconut Lab Pte Ltd",
    "currency": null,
    "end_sal": null,
    "exp_min": 1,
    "exp_opt": 3,
    "last_updated": 18,
    "location": "Jakarta",
    "start_sal": null,
    "title": "Fullstack WordPress Developer - Woocommerce (REMOTE)"
},{
    "_id": "610f632b0112f1b4448d9758",
    "applicant": 16,
    "company": "Pt Bintang Digital Teknologi Servis Indonesia",
    "currency": "IDR",
    "end_sal": 10000000,
    "exp_min": 3,
    "exp_opt": 5,
    "last_updated": 11,
    "location": "Kuningan, Jakarta",
    "start_sal": 5000000,
    "title": "Implementor IT"
},{
    "_id": "610f632b0112f1b4448d9759",
    "applicant": 73,
    "company": "Pt Sinergi Inti Berkah Investama",
    "currency": "IDR",
    "end_sal": 2000000,
    "exp_min": 0,
    "exp_opt": 1,
    "last_updated": 2,
    "location": "Surabaya",
    "start_sal": 600000,
    "title": "Internship Web Programmer"
},{
    "_id": "610f632b0112f1b4448d975a",
    "applicant": 129,
    "company": "PT Visionet Data Internasional",
    "currency": "IDR",
    "end_sal": 11000000,
    "exp_min": 3,
    "exp_opt": 5,
    "last_updated": 2,
    "location": "Tangerang",
    "start_sal": 7000000,
    "title": "Network Engineer"
},{
    "_id": "610f632b0112f1b4448d975b",
    "applicant": 11,
    "company": "Rimba Ananta Vikasa Indonesia",
    "currency": null,
    "end_sal": null,
    "exp_min": 1,
    "exp_opt": 3,
    "last_updated": 3,
    "location": "Bandung",
    "start_sal": null,
    "title": "Junior Programmer"
},{
    "_id": "610f632b0112f1b4448d975c",
    "applicant": 9,
    "company": "Piksel Digital Media",
    "currency": "IDR",
    "end_sal": 1850000,
    "exp_min": null,
    "exp_opt": null,
    "last_updated": 18,
    "location": "Jember",
    "start_sal": 1500000,
    "title": "QA Engineer"
},{
    "_id": "610f632b0112f1b4448d975d",
    "applicant": 63,
    "company": "Justnile Sea Pte Ltd",
    "currency": "IDR",
    "end_sal": 10000000,
    "exp_min": 1,
    "exp_opt": 3,
    "last_updated": 1,
    "location": "Medan",
    "start_sal": 3000000,
    "title": "PROGRAMMER-FULL TIME (MEDAN)"
},{
    "_id": "610f632b0112f1b4448d975e",
    "applicant": 67,
    "company": "Pt Platinumetrix Global Inovasi",
    "currency": "IDR",
    "end_sal": 13000000,
    "exp_min": 1,
    "exp_opt": 3,
    "last_updated": 2,
    "location": "Jakarta",
    "start_sal": 6500000,
    "title": "Front End Developer"
},{
    "_id": "610f632b0112f1b4448d975f",
    "applicant": 233,
    "company": "Pt Super Giga Generasi",
    "currency": "IDR",
    "end_sal": 2500000,
    "exp_min": 0,
    "exp_opt": 1,
    "last_updated": 2,
    "location": "Kembangan, Jakarta",
    "start_sal": 2000000,
    "title": "Backend Engineer Intern"
},{
    "_id": "610f632b0112f1b4448d9760",
    "applicant": 256,
    "company": "Avana Indonesia",
    "currency": "IDR",
    "end_sal": 15000000,
    "exp_min": 1,
    "exp_opt": 3,
    "last_updated": null,
    "location": "Bandung",
    "start_sal": 8000000,
    "title": "PHP Developer"
}]